mitm6/__init__.py
mitm6/mitm6.py
mitm6-0.3.0.dist-info/LICENSE
mitm6-0.3.0.dist-info/METADATA
mitm6-0.3.0.dist-info/WHEEL
mitm6-0.3.0.dist-info/entry_points.txt
mitm6-0.3.0.dist-info/top_level.txt
mitm6-0.3.0.dist-info/RECORD
